{
  "custom": [
    {
      "name": "Acorn Heights - A",
      "x": 950.4538137347969,
      "y": 117.93581930036957
    },
    {
      "name": "Acorn Heights - B",
      "x": 953.9613213066225,
      "y": 121.28389470895357
    },
    {
      "name": "Acorn Heights - C",
      "x": 961.2952007730446,
      "y": 109.00761821081228
    },
    {
      "name": "Acorn Heights - D",
      "x": 933.713436699173,
      "y": 126.86402038992688
    },
    {
      "name": "Acorn Heights - E",
      "x": 929.4087683167079,
      "y": 118.09525146268311
    },
    {
      "name": "Airship Fortress - A",
      "x": 520.2370193937126,
      "y": 339.3427849161603
    },
    {
      "name": "Airship Fortress - B",
      "x": 529.2037176834505,
      "y": 334.5313858338619
    },
    {
      "name": "Airship Fortress - C",
      "x": 502.30362281423675,
      "y": 345.2476837898902
    },
    {
      "name": "Airship Fortress - D",
      "x": 480.8710269021803,
      "y": 333.875285959003
    },
    {
      "name": "Airship Fortress - E",
      "x": 490.2751251084908,
      "y": 338.9053849995877
    },
    {
      "name": "Boo Cinema - A",
      "x": 1134.4385290132745,
      "y": 186.01335262767617
    },
    {
      "name": "Boo Cinema - B",
      "x": 1147.033669836043,
      "y": 182.82470938140568
    },
    {
      "name": "Boo Cinema - C",
      "x": 1132.5253430655123,
      "y": 174.69366910341603
    },
    {
      "name": "Boo Cinema - D",
      "x": 1137.7866044218586,
      "y": 172.93991531796726
    },
    {
      "name": "Boo Cinema - E",
      "x": 1135.0762576625286,
      "y": 163.0551212545288
    },
    {
      "name": "Bowser's Castle - A",
      "x": 674.2017900512994,
      "y": 225.83750655748096
    },
    {
      "name": "Bowser's Castle - B",
      "x": 678.5757892170252,
      "y": 213.15290897687615
    },
    {
      "name": "Bowser's Castle - C",
      "x": 668.5155911358559,
      "y": 203.09271089570677
    },
    {
      "name": "Bowser's Castle - D",
      "x": 645.3333955647379,
      "y": 195.6569123139729
    },
    {
      "name": "Bowser's Castle - E",
      "x": 640.7406964407257,
      "y": 205.93581035342856
    },
    {
      "name": "Cheep Cheep Falls - A",
      "x": 1140.9062081966847,
      "y": 586.5559856282962
    },
    {
      "name": "Cheep Cheep Falls - B",
      "x": 1131.8520357344592,
      "y": 571.4000882307477
    },
    {
      "name": "Cheep Cheep Falls - C",
      "x": 1143.6618259071581,
      "y": 548.370997390445
    },
    {
      "name": "Cheep Cheep Falls - D",
      "x": 1119.0580963702316,
      "y": 550.3392957458685
    },
    {
      "name": "Cheep Cheep Falls - E",
      "x": 1120.82956489656,
      "y": 562.9364052608862
    },
    {
      "name": "Choco Mountain - A",
      "x": 793.2039509742785,
      "y": 570.2152283145638
    },
    {
      "name": "Choco Mountain - B",
      "x": 814.3449407814581,
      "y": 549.0742385118681
    },
    {
      "name": "Choco Mountain - C",
      "x": 803.652945937783,
      "y": 556.1212351142611
    },
    {
      "name": "Choco Mountain - D",
      "x": 810.213942774494,
      "y": 557.5792344113081
    },
    {
      "name": "Choco Mountain - E",
      "x": 816.2889398455226,
      "y": 564.8692308965424
    },
    {
      "name": "Crown City - A",
      "x": 784.8664844372357,
      "y": 828.8605151006332
    },
    {
      "name": "Crown City - B",
      "x": 801.1730479280458,
      "y": 823.6720630854512
    },
    {
      "name": "Crown City - C",
      "x": 811.364650111211,
      "y": 826.8221946666695
    },
    {
      "name": "Crown City - D",
      "x": 801.9142553595486,
      "y": 789.391219375772
    },
    {
      "name": "Crown City - E",
      "x": 788.2019178767447,
      "y": 786.6116915076361
    },
    {
      "name": "Crown City - F",
      "x": 800.8024442083031,
      "y": 776.6053911830204
    },
    {
      "name": "Crown City - G",
      "x": 808.2145185233323,
      "y": 784.0174654980497
    },
    {
      "name": "Crown City - H",
      "x": 821.9268560061363,
      "y": 800.5093308489895
    },
    {
      "name": "Crown City - I",
      "x": 825.2622894478994,
      "y": 759.9282239699806
    },
    {
      "name": "Crown City - J",
      "x": 855.8370959962051,
      "y": 766.7843927051628
    },
    {
      "name": "Dandelion Depths - A",
      "x": 1145.2799160648938,
      "y": 391.3619776964111
    },
    {
      "name": "Dandelion Depths - B",
      "x": 1125.3508957757035,
      "y": 390.724249047157
    },
    {
      "name": "Dandelion Depths - C",
      "x": 1109.7265438689783,
      "y": 390.8836812094705
    },
    {
      "name": "Dandelion Depths - D",
      "x": 1115.4661017078256,
      "y": 395.5072139165627
    },
    {
      "name": "Dandelion Depths - E",
      "x": 1130.6121571276103,
      "y": 404.116550681493
    },
    {
      "name": "Desert Hills - A",
      "x": 471.1899965737343,
      "y": 758.8625893496094
    },
    {
      "name": "Desert Hills - B",
      "x": 458.5928958621399,
      "y": 757.6816111508082
    },
    {
      "name": "Desert Hills - C",
      "x": 467.253402601361,
      "y": 770.2787118624026
    },
    {
      "name": "Desert Hills - D",
      "x": 460.95485224556387,
      "y": 772.8374979444452
    },
    {
      "name": "Desert Hills - E",
      "x": 474.33927175163285,
      "y": 785.8282580532768
    },
    {
      "name": "Dino Dino Jungle - A",
      "x": 1138.3968108578715,
      "y": 972.7196107159522
    },
    {
      "name": "Dino Dino Jungle - B",
      "x": 1128.0656017589158,
      "y": 973.5805448075319
    },
    {
      "name": "Dino Dino Jungle - C",
      "x": 1135.096563503997,
      "y": 977.311259204377
    },
    {
      "name": "Dino Dino Jungle - D",
      "x": 1124.765354405041,
      "y": 981.1854626193048
    },
    {
      "name": "Dino Dino Jungle - E",
      "x": 1131.3658491071517,
      "y": 984.3422209550969
    },
    {
      "name": "DK Pass - A",
      "x": 1273.9631774806767,
      "y": 460.1912306993076
    },
    {
      "name": "DK Pass - B",
      "x": 1265.1058348440909,
      "y": 479.8742143266825
    },
    {
      "name": "DK Pass - C",
      "x": 1264.7121751777074,
      "y": 469.6390628447147
    },
    {
      "name": "DK Pass - D",
      "x": 1255.4611728728414,
      "y": 458.22293234083736
    },
    {
      "name": "DK Pass - E",
      "x": 1248.3752987669864,
      "y": 469.44223300844095
    },
    {
      "name": "DK Spaceport - A",
      "x": 758.1785380144916,
      "y": 983.8104044497012
    },
    {
      "name": "DK Spaceport - B",
      "x": 801.5118713180225,
      "y": 940.4770711163679
    },
    {
      "name": "DK Spaceport - C",
      "x": 813.5118713180225,
      "y": 940.1437377830346
    },
    {
      "name": "DK Spaceport - D",
      "x": 808.1785379846892,
      "y": 958.8104044497013
    },
    {
      "name": "DK Spaceport - E",
      "x": 817.5118713180225,
      "y": 952.1437377830346
    },
    {
      "name": "Dry Bones Burnout - A",
      "x": 820.6632726640338,
      "y": 177.4454123259588
    },
    {
      "name": "Dry Bones Burnout - B",
      "x": 802.0332752303711,
      "y": 167.9954136277241
    },
    {
      "name": "Dry Bones Burnout - C",
      "x": 799.8009909462821,
      "y": 172.3107855697849
    },
    {
      "name": "Dry Bones Burnout - D",
      "x": 800.3749469830078,
      "y": 187.9510875645596
    },
    {
      "name": "Dry Bones Burnout - E",
      "x": 820.8938752959507,
      "y": 189.24248864719232
    },
    {
      "name": "Faraway Oasis - A",
      "x": 1143.2202997438933,
      "y": 793.7901800609145
    },
    {
      "name": "Faraway Oasis - B",
      "x": 1131.8041631915312,
      "y": 785.5233225574798
    },
    {
      "name": "Faraway Oasis - C",
      "x": 1144.4012793872412,
      "y": 763.4783692149874
    },
    {
      "name": "Faraway Oasis - D",
      "x": 1156.998395582951,
      "y": 749.1097835542558
    },
    {
      "name": "Faraway Oasis - E",
      "x": 1122.9468158664226,
      "y": 747.73197397035
    },
    {
      "name": "Great ? Block Ruins - A",
      "x": 1336.5551409871061,
      "y": 901.1185921035694
    },
    {
      "name": "Great ? Block Ruins - B",
      "x": 1335.2637398497368,
      "y": 910.1584000679752
    },
    {
      "name": "Great ? Block Ruins - C",
      "x": 1319.0494811221672,
      "y": 918.6242519713279
    },
    {
      "name": "Great ? Block Ruins - D",
      "x": 1320.3408822595368,
      "y": 907.8625758265822
    },
    {
      "name": "Great ? Block Ruins - E",
      "x": 1297.8131068632024,
      "y": 907.1451307502658
    },
    {
      "name": "Koopa Troopa Beach - A",
      "x": 964.9185914583406,
      "y": 902.5534822372797
    },
    {
      "name": "Koopa Troopa Beach - B",
      "x": 957.4571626646502,
      "y": 907.4321087590504
    },
    {
      "name": "Koopa Troopa Beach - C",
      "x": 949.99573387096,
      "y": 913.3151583848447
    },
    {
      "name": "Koopa Troopa Beach - D",
      "x": 941.673370979209,
      "y": 899.6837019348334
    },
    {
      "name": "Koopa Troopa Beach - E",
      "x": 907.8099633770761,
      "y": 905.4232625461689
    },
    {
      "name": "Mario Bros. Circuit - A",
      "x": 610.1607146830047,
      "y": 681.654852083329
    },
    {
      "name": "Mario Bros. Circuit - B",
      "x": 608.2695239916642,
      "y": 671.2533032809565
    },
    {
      "name": "Mario Bros. Circuit - C",
      "x": 620.8324335841402,
      "y": 669.2270275402345
    },
    {
      "name": "Mario Bros. Circuit - D",
      "x": 634.0707684337539,
      "y": 662.8780302223958
    },
    {
      "name": "Mario Bros. Circuit - E",
      "x": 612.3220754833385,
      "y": 661.5271797285811
    },
    {
      "name": "Mario Circuit - A",
      "x": 958.9037183299172,
      "y": 294.9055194961471
    },
    {
      "name": "Mario Circuit - B",
      "x": 969.9045375295503,
      "y": 293.948926522266
    },
    {
      "name": "Mario Circuit - C",
      "x": 969.7451053672369,
      "y": 289.3253938151738
    },
    {
      "name": "Mario Circuit - D",
      "x": 969.7451053672369,
      "y": 282.31037867337875
    },
    {
      "name": "Mario Circuit - E",
      "x": 993.181633229763,
      "y": 285.8178862442762
    },
    {
      "name": "Moo Moo Meadows - A",
      "x": 965.841577233315,
      "y": 465.9763887432621
    },
    {
      "name": "Moo Moo Meadows - B",
      "x": 968.0498719380201,
      "y": 463.4194159272878
    },
    {
      "name": "Moo Moo Meadows - C",
      "x": 957.4733025655906,
      "y": 455.0511412568263
    },
    {
      "name": "Moo Moo Meadows - D",
      "x": 955.9623640855492,
      "y": 484.92123278889017
    },
    {
      "name": "Moo Moo Meadows - E",
      "x": 983.1592567625727,
      "y": 484.3401026034415
    },
    {
      "name": "Peach Beach - A",
      "x": 1404.8072906885689,
      "y": 774.3040159550496
    },
    {
      "name": "Peach Beach - B",
      "x": 1407.1692499752644,
      "y": 780.6025740529045
    },
    {
      "name": "Peach Beach - C",
      "x": 1398.3119026501558,
      "y": 798.5140986479705
    },
    {
      "name": "Peach Beach - D",
      "x": 1412.0899984892137,
      "y": 762.4942195258625
    },
    {
      "name": "Peach Beach - E",
      "x": 1442.2049793945828,
      "y": 779.0279345327317
    },
    {
      "name": "Peach Stadium - A",
      "x": 942.0927185014642,
      "y": 660.9216213893415
    },
    {
      "name": "Peach Stadium - B",
      "x": 933.0050823607123,
      "y": 650.5585275446244
    },
    {
      "name": "Peach Stadium - C",
      "x": 966.166982663807,
      "y": 645.4566967287637
    },
    {
      "name": "Peach Stadium - D",
      "x": 970.3122202016938,
      "y": 633.1804163280989
    },
    {
      "name": "Peach Stadium - E",
      "x": 960.5868552089593,
      "y": 625.0493734653209
    },
    {
      "name": "Salty Salty Speedway - A",
      "x": 1278.6266210184442,
      "y": 689.7242444237056
    },
    {
      "name": "Salty Salty Speedway - B",
      "x": 1247.3460223202735,
      "y": 673.9404560897663
    },
    {
      "name": "Salty Salty Speedway - C",
      "x": 1252.2246478053094,
      "y": 700.6294072760355
    },
    {
      "name": "Salty Salty Speedway - D",
      "x": 1274.7524184273864,
      "y": 674.3709230477546
    },
    {
      "name": "Salty Salty Speedway - E",
      "x": 1305.0285942315793,
      "y": 666.7660068504929
    },
    {
      "name": "Shy Guy Bazaar - A",
      "x": 451.17853800455725,
      "y": 561.8104043106237
    },
    {
      "name": "Shy Guy Bazaar - B",
      "x": 447.47625269205525,
      "y": 553.2426402315293
    },
    {
      "name": "Shy Guy Bazaar - C",
      "x": 444.1104607263466,
      "y": 561.7456936185827
    },
    {
      "name": "Shy Guy Bazaar - D",
      "x": 441.4532565428924,
      "y": 546.8653501912393
    },
    {
      "name": "Shy Guy Bazaar - E",
      "x": 480.4255845668871,
      "y": 550.585436048075
    },
    {
      "name": "Sky-High Sundae - A",
      "x": 1416.9115515753504,
      "y": 397.0456279570273
    },
    {
      "name": "Sky-High Sundae - B",
      "x": 1424.6616822950923,
      "y": 407.2773806497434
    },
    {
      "name": "Sky-High Sundae - C",
      "x": 1428.6007593506474,
      "y": 389.7484877525229
    },
    {
      "name": "Sky-High Sundae - D",
      "x": 1398.072912169514,
      "y": 379.5725386928817
    },
    {
      "name": "Sky-High Sundae - E",
      "x": 1401.2241738139583,
      "y": 386.26896968732547
    },
    {
      "name": "Starview Peak - A",
      "x": 1265.7961874948112,
      "y": 281.0082295155085
    },
    {
      "name": "Starview Peak - B",
      "x": 1264.1948139736767,
      "y": 282.99088244441856
    },
    {
      "name": "Starview Peak - C",
      "x": 1261.220834578577,
      "y": 286.80367654070017
    },
    {
      "name": "Starview Peak - D",
      "x": 1265.7199316052254,
      "y": 276.50913248419556
    },
    {
      "name": "Starview Peak - E",
      "x": 1262.5171845643488,
      "y": 278.79680894196446
    },
    {
      "name": "Toad's Factory - A",
      "x": 803.5050572462674,
      "y": 385.3640536745901
    },
    {
      "name": "Toad's Factory - B",
      "x": 812.777415624095,
      "y": 396.63935366486226
    },
    {
      "name": "Toad's Factory - C",
      "x": 815.6471947890126,
      "y": 386.11683006016443
    },
    {
      "name": "Toad's Factory - D",
      "x": 808.47274687855,
      "y": 363.9557576199676
    },
    {
      "name": "Toad's Factory - E",
      "x": 790.8138834635416,
      "y": 361.6168314615885
    },
    {
      "name": "Wario Shipyard - A",
      "x": 1445.71456308984,
      "y": 586.0371057670227
    },
    {
      "name": "Wario Shipyard - B",
      "x": 1441.2292250996563,
      "y": 599.572078258125
    },
    {
      "name": "Wario Shipyard - C",
      "x": 1433.7890565395396,
      "y": 585.2231817493284
    },
    {
      "name": "Wario Shipyard - D",
      "x": 1422.0044490111188,
      "y": 592.8944426819469
    },
    {
      "name": "Wario Shipyard - E",
      "x": 1412.1252348116518,
      "y": 586.8506881128611
    },
    {
      "name": "Wario Stadium - A",
      "x": 658.4582648085523,
      "y": 448.54879538328305
    },
    {
      "name": "Wario Stadium - B",
      "x": 664.6584079032788,
      "y": 455.45752626026393
    },
    {
      "name": "Wario Stadium - C",
      "x": 664.3041140121516,
      "y": 443.2343870163747
    },
    {
      "name": "Wario Stadium - D",
      "x": 654.7381789517165,
      "y": 489.6468867457607
    },
    {
      "name": "Wario Stadium - E",
      "x": 630.0243984440294,
      "y": 481.06035788567647
    },
    {
      "name": "Whistlestop Summit - A",
      "x": 625.8774903450709,
      "y": 863.1413587743725
    },
    {
      "name": "Whistlestop Summit - B",
      "x": 634.9572813809816,
      "y": 882.5980538513242
    },
    {
      "name": "Whistlestop Summit - C",
      "x": 630.5100367919642,
      "y": 886.1187891456245
    },
    {
      "name": "Whistlestop Summit - D",
      "x": 604.0118711199842,
      "y": 896.3103913258875
    },
    {
      "name": "Whistlestop Summit - E",
      "x": 611.1785380045574,
      "y": 904.1437377830346
    }
  ]
}
